{
  "$schema": "../../armor.schema.json",
  "key": "DRAGON_HELM",
  "name": "Dragon Helm",
  "img": "public/img/items/dragon/dragon-helm.webp",
  "type": "HELM",
  "normalLevels": [
    { "defense": 24, "requiredStrength": 225, "requiredAgility": 71 },
    { "defense": 27, "requiredStrength": 236, "requiredAgility": 74 },
    { "defense": 30, "requiredStrength": 246, "requiredAgility": 76 },
    { "defense": 33, "requiredStrength": 257, "requiredAgility": 79 },
    { "defense": 36, "requiredStrength": 268, "requiredAgility": 82 },
    { "defense": 39, "requiredStrength": 279, "requiredAgility": 84 },
    { "defense": 42, "requiredStrength": 290, "requiredAgility": 87 },
    { "defense": 45, "requiredStrength": 300, "requiredAgility": 90 },
    { "defense": 48, "requiredStrength": 311, "requiredAgility": 92 },
    { "defense": 51, "requiredStrength": 322, "requiredAgility": 95 },
    { "defense": 55, "requiredStrength": 333, "requiredAgility": 98 },
    { "defense": 60, "requiredStrength": 344, "requiredAgility": 101 },
    { "defense": 66, "requiredStrength": 354, "requiredAgility": 103 },
    { "defense": 73, "requiredStrength": 365, "requiredAgility": 106 },
    { "defense": 81, "requiredStrength": 376, "requiredAgility": 109 },
    { "defense": 90, "requiredStrength": 387, "requiredAgility": 111 }
  ],
  "excellentLevels": [
    { "defense": 44, "requiredStrength": 315, "requiredAgility": 93 },
    { "defense": 47, "requiredStrength": 326, "requiredAgility": 96 },
    { "defense": 50, "requiredStrength": 336, "requiredAgility": 99 },
    { "defense": 53, "requiredStrength": 347, "requiredAgility": 101 },
    { "defense": 56, "requiredStrength": 358, "requiredAgility": 104 },
    { "defense": 59, "requiredStrength": 369, "requiredAgility": 107 },
    { "defense": 62, "requiredStrength": 380, "requiredAgility": 110 },
    { "defense": 65, "requiredStrength": 390, "requiredAgility": 112 },
    { "defense": 68, "requiredStrength": 401, "requiredAgility": 115 },
    { "defense": 71, "requiredStrength": 412, "requiredAgility": 118 },
    { "defense": 75, "requiredStrength": 423, "requiredAgility": 120 },
    { "defense": 80, "requiredStrength": 434, "requiredAgility": 123 },
    { "defense": 86, "requiredStrength": 444, "requiredAgility": 126 },
    { "defense": 93, "requiredStrength": 455, "requiredAgility": 128 },
    { "defense": 101, "requiredStrength": 466, "requiredAgility": 131 },
    { "defense": 110, "requiredStrength": 477, "requiredAgility": 134 }
  ],
  "ancientLevels": [
    { "defense": 49, "requiredStrength": 315, "requiredAgility": 93 },
    { "defense": 52, "requiredStrength": 326, "requiredAgility": 96 },
    { "defense": 55, "requiredStrength": 336, "requiredAgility": 99 },
    { "defense": 58, "requiredStrength": 347, "requiredAgility": 101 },
    { "defense": 61, "requiredStrength": 358, "requiredAgility": 104 },
    { "defense": 64, "requiredStrength": 369, "requiredAgility": 107 },
    { "defense": 67, "requiredStrength": 380, "requiredAgility": 110 },
    { "defense": 70, "requiredStrength": 390, "requiredAgility": 112 },
    { "defense": 73, "requiredStrength": 401, "requiredAgility": 115 },
    { "defense": 76, "requiredStrength": 412, "requiredAgility": 118 },
    { "defense": 80, "requiredStrength": 423, "requiredAgility": 120 },
    { "defense": 85, "requiredStrength": 434, "requiredAgility": 123 },
    { "defense": 91, "requiredStrength": 444, "requiredAgility": 126 },
    { "defense": 98, "requiredStrength": 455, "requiredAgility": 128 }
  ]
}
