{
  "$schema": "../../weapon.schema.json",
  "key": "CRESCENT_AXE",
  "name": "Crescent Axe",
  "img": "public/img/items/axes/crescent-axe.webp",
  "requiredCharacterKeys": ["DARK_WIZARD", "DARK_KNIGHT", "MAGIC_GLADIATOR"],
  "type": "WEAPON",
  "twoHands": true,
  "attackSpeed": 30,
  "durability": 59,
  "version": "0.45",
  "normalLevels": [
    { "minDamage": 69, "maxDamage": 89, "requiredStrength": 182, "requiredAgility": 84 },
    { "minDamage": 72, "maxDamage": 92, "requiredStrength": 191, "requiredAgility": 88 },
    { "minDamage": 75, "maxDamage": 95, "requiredStrength": 200, "requiredAgility": 92 },
    { "minDamage": 78, "maxDamage": 98, "requiredStrength": 209, "requiredAgility": 95 },
    { "minDamage": 81, "maxDamage": 101, "requiredStrength": 218, "requiredAgility": 99 },
    { "minDamage": 84, "maxDamage": 104, "requiredStrength": 227, "requiredAgility": 102 },
    { "minDamage": 87, "maxDamage": 107, "requiredStrength": 236, "requiredAgility": 106 },
    { "minDamage": 90, "maxDamage": 110, "requiredStrength": 245, "requiredAgility": 110 },
    { "minDamage": 93, "maxDamage": 113, "requiredStrength": 254, "requiredAgility": 113 },
    { "minDamage": 96, "maxDamage": 116, "requiredStrength": 263, "requiredAgility": 117 },
    { "minDamage": 100, "maxDamage": 120, "requiredStrength": 272, "requiredAgility": 120 },
    { "minDamage": 105, "maxDamage": 125, "requiredStrength": 281, "requiredAgility": 124 },
    { "minDamage": 111, "maxDamage": 131, "requiredStrength": 290, "requiredAgility": 128 },
    { "minDamage": 118, "maxDamage": 138, "requiredStrength": 299, "requiredAgility": 131 },
    { "minDamage": 126, "maxDamage": 146, "requiredStrength": 308, "requiredAgility": 135 },
    { "minDamage": 135, "maxDamage": 155, "requiredStrength": 317, "requiredAgility": 138 }
  ],
  "excellentLevels": [
    { "minDamage": 105, "maxDamage": 125, "requiredStrength": 257, "requiredAgility": 114 },
    { "minDamage": 108, "maxDamage": 128, "requiredStrength": 266, "requiredAgility": 118 },
    { "minDamage": 111, "maxDamage": 131, "requiredStrength": 275, "requiredAgility": 122 },
    { "minDamage": 114, "maxDamage": 134, "requiredStrength": 284, "requiredAgility": 125 },
    { "minDamage": 117, "maxDamage": 137, "requiredStrength": 293, "requiredAgility": 129 },
    { "minDamage": 120, "maxDamage": 140, "requiredStrength": 302, "requiredAgility": 132 },
    { "minDamage": 123, "maxDamage": 143, "requiredStrength": 311, "requiredAgility": 136 },
    { "minDamage": 126, "maxDamage": 146, "requiredStrength": 320, "requiredAgility": 140 },
    { "minDamage": 129, "maxDamage": 149, "requiredStrength": 329, "requiredAgility": 143 },
    { "minDamage": 132, "maxDamage": 152, "requiredStrength": 338, "requiredAgility": 147 },
    { "minDamage": 136, "maxDamage": 156, "requiredStrength": 347, "requiredAgility": 150 },
    { "minDamage": 141, "maxDamage": 161, "requiredStrength": 356, "requiredAgility": 154 },
    { "minDamage": 147, "maxDamage": 167, "requiredStrength": 365, "requiredAgility": 158 },
    { "minDamage": 154, "maxDamage": 174, "requiredStrength": 374, "requiredAgility": 161 },
    { "minDamage": 162, "maxDamage": 182, "requiredStrength": 383, "requiredAgility": 165 },
    { "minDamage": 171, "maxDamage": 191, "requiredStrength": 392, "requiredAgility": 168 }
  ]
}
