{
  "$schema": "../../gloves.schema.json",
  "key": "ECLIPSE_GLOVES",
  "name": "Eclipse Gloves",
  "img": "public/img/items/eclipse/eclipse-gloves.webp",
  "type": "GLOVES",
  "attackSpeed": 6,
  "normalLevels": [
    { "defense": 15, "requiredStrength": 116, "requiredAgility": 41 },
    { "defense": 18, "requiredStrength": 121, "requiredAgility": 43 },
    { "defense": 21, "requiredStrength": 126, "requiredAgility": 44 },
    { "defense": 24, "requiredStrength": 131, "requiredAgility": 45 },
    { "defense": 27, "requiredStrength": 136, "requiredAgility": 46 },
    { "defense": 30, "requiredStrength": 140, "requiredAgility": 47 },
    { "defense": 33, "requiredStrength": 145, "requiredAgility": 48 },
    { "defense": 36, "requiredStrength": 150, "requiredAgility": 49 },
    { "defense": 39, "requiredStrength": 155, "requiredAgility": 50 },
    { "defense": 42, "requiredStrength": 159, "requiredAgility": 51 },
    { "defense": 46, "requiredStrength": 164, "requiredAgility": 52 },
    { "defense": 51, "requiredStrength": 169, "requiredAgility": 53 },
    { "defense": 57, "requiredStrength": 174, "requiredAgility": 54 },
    { "defense": 64, "requiredStrength": 179, "requiredAgility": 56 },
    { "defense": 72, "requiredStrength": 183, "requiredAgility": 57 },
    { "defense": 81, "requiredStrength": 188, "requiredAgility": 58 }
  ],
  "excellentLevels": [
    { "defense": 33, "requiredStrength": 156, "requiredAgility": 50 },
    { "defense": 36, "requiredStrength": 161, "requiredAgility": 52 },
    { "defense": 39, "requiredStrength": 166, "requiredAgility": 53 },
    { "defense": 42, "requiredStrength": 171, "requiredAgility": 54 },
    { "defense": 45, "requiredStrength": 175, "requiredAgility": 55 },
    { "defense": 48, "requiredStrength": 180, "requiredAgility": 56 },
    { "defense": 51, "requiredStrength": 185, "requiredAgility": 57 },
    { "defense": 54, "requiredStrength": 190, "requiredAgility": 58 },
    { "defense": 57, "requiredStrength": 194, "requiredAgility": 59 },
    { "defense": 60, "requiredStrength": 199, "requiredAgility": 60 },
    { "defense": 64, "requiredStrength": 204, "requiredAgility": 61 },
    { "defense": 69, "requiredStrength": 209, "requiredAgility": 62 },
    { "defense": 75, "requiredStrength": 213, "requiredAgility": 63 },
    { "defense": 82, "requiredStrength": 218, "requiredAgility": 65 },
    { "defense": 90, "requiredStrength": 223, "requiredAgility": 66 },
    { "defense": 99, "requiredStrength": 228, "requiredAgility": 67 }
  ]
}
